setup.py
TxPx.egg-info/PKG-INFO
TxPx.egg-info/SOURCES.txt
TxPx.egg-info/dependency_links.txt
TxPx.egg-info/not-zip-safe
TxPx.egg-info/requires.txt
TxPx.egg-info/top_level.txt
txpx/__init__.py
txpx/process.py
txpx/test/__init__.py
txpx/test/test_cli_util.py
txpx/test/test_process.py