Metadata-Version: 1.0
Name: TxPx
Version: 0.1
Summary: Robust process management and communication for Twisted
Home-page: http://github.com/Brightmd/TxPx
Author: Bright.md
Author-email: support@bright.md
License: MIT
Platform: UNKNOWN
